[
  {
    "idx": 1,
    "status_code": 202,
    "ok": true,
    "elapsed_s": 0.093,
    "body": "{\"page_id\":\"def16a6a1cf149d18f68cb13a7e43b06\",\"document_id\":\"5efe1fb0afed4cbc983e000e1a5b6474\",\"page_number\":2,\"content_sha256\":\"338b4b3bb7f15efb4eee1414d1efaced81314d75cb1cc25238941dcbcb0676d6\",\"status\":\"accepted\",\"created_at\":\"2026-06-04T15:22:52.479389+00:00\"}"
  },
  {
    "idx": 2,
    "status_code": 202,
    "ok": true,
    "elapsed_s": 0.103,
    "body": "{\"page_id\":\"97a80af9df854df98448021cfa1d5c7c\",\"document_id\":\"5efe1fb0afed4cbc983e000e1a5b6474\",\"page_number\":3,\"content_sha256\":\"338b4b3bb7f15efb4eee1414d1efaced81314d75cb1cc25238941dcbcb0676d6\",\"status\":\"accepted\",\"created_at\":\"2026-06-04T15:22:52.488504+00:00\"}"
  },
  {
    "idx": 0,
    "status_code": 202,
    "ok": true,
    "elapsed_s": 0.11,
    "body": "{\"page_id\":\"6a08c47ed48d450dafc8949bddf11bd2\",\"document_id\":\"5efe1fb0afed4cbc983e000e1a5b6474\",\"page_number\":1,\"content_sha256\":\"338b4b3bb7f15efb4eee1414d1efaced81314d75cb1cc25238941dcbcb0676d6\",\"status\":\"accepted\",\"created_at\":\"2026-06-04T15:22:52.483752+00:00\"}"
  },
  {
    "idx": 4,
    "status_code": 202,
    "ok": true,
    "elapsed_s": 0.121,
    "body": "{\"page_id\":\"0376c32dcc344170860ba9da5864b0df\",\"document_id\":\"5efe1fb0afed4cbc983e000e1a5b6474\",\"page_number\":5,\"content_sha256\":\"338b4b3bb7f15efb4eee1414d1efaced81314d75cb1cc25238941dcbcb0676d6\",\"status\":\"accepted\",\"created_at\":\"2026-06-04T15:22:52.520673+00:00\"}"
  },
  {
    "idx": 5,
    "status_code": 202,
    "ok": true,
    "elapsed_s": 0.182,
    "body": "{\"page_id\":\"0ae942a2c1d749f3a3ba81fb6f61d8f9\",\"document_id\":\"5efe1fb0afed4cbc983e000e1a5b6474\",\"page_number\":6,\"content_sha256\":\"338b4b3bb7f15efb4eee1414d1efaced81314d75cb1cc25238941dcbcb0676d6\",\"status\":\"accepted\",\"created_at\":\"2026-06-04T15:22:52.524406+00:00\"}"
  },
  {
    "idx": 8,
    "status_code": 429,
    "ok": false,
    "elapsed_s": 0.19,
    "body": "{\"detail\":\"realtime pipeline is at capacity \u2014 try again shortly\"}"
  },
  {
    "idx": 9,
    "status_code": 429,
    "ok": false,
    "elapsed_s": 0.194,
    "body": "{\"detail\":\"realtime pipeline is at capacity \u2014 try again shortly\"}"
  },
  {
    "idx": 10,
    "status_code": 429,
    "ok": false,
    "elapsed_s": 0.274,
    "body": "{\"detail\":\"realtime pipeline is at capacity \u2014 try again shortly\"}"
  },
  {
    "idx": 11,
    "status_code": 429,
    "ok": false,
    "elapsed_s": 0.273,
    "body": "{\"detail\":\"realtime pipeline is at capacity \u2014 try again shortly\"}"
  },
  {
    "idx": 13,
    "status_code": 429,
    "ok": false,
    "elapsed_s": 0.278,
    "body": "{\"detail\":\"realtime pipeline is at capacity \u2014 try again shortly\"}"
  },
  {
    "idx": 12,
    "status_code": 429,
    "ok": false,
    "elapsed_s": 0.28,
    "body": "{\"detail\":\"realtime pipeline is at capacity \u2014 try again shortly\"}"
  },
  {
    "idx": 7,
    "status_code": 429,
    "ok": false,
    "elapsed_s": 0.288,
    "body": "{\"detail\":\"realtime pipeline is at capacity \u2014 try again shortly\"}"
  },
  {
    "idx": 16,
    "status_code": 429,
    "ok": false,
    "elapsed_s": 0.206,
    "body": "{\"detail\":\"realtime pipeline is at capacity \u2014 try again shortly\"}"
  },
  {
    "idx": 3,
    "status_code": 429,
    "ok": false,
    "elapsed_s": 0.299,
    "body": "{\"detail\":\"realtime pipeline is at capacity \u2014 try again shortly\"}"
  },
  {
    "idx": 6,
    "status_code": 429,
    "ok": false,
    "elapsed_s": 0.299,
    "body": "{\"detail\":\"realtime pipeline is at capacity \u2014 try again shortly\"}"
  },
  {
    "idx": 17,
    "status_code": 429,
    "ok": false,
    "elapsed_s": 0.206,
    "body": "{\"detail\":\"realtime pipeline is at capacity \u2014 try again shortly\"}"
  },
  {
    "idx": 14,
    "status_code": 429,
    "ok": false,
    "elapsed_s": 0.285,
    "body": "{\"detail\":\"realtime pipeline is at capacity \u2014 try again shortly\"}"
  },
  {
    "idx": 18,
    "status_code": 429,
    "ok": false,
    "elapsed_s": 0.204,
    "body": "{\"detail\":\"realtime pipeline is at capacity \u2014 try again shortly\"}"
  },
  {
    "idx": 19,
    "status_code": 429,
    "ok": false,
    "elapsed_s": 0.184,
    "body": "{\"detail\":\"realtime pipeline is at capacity \u2014 try again shortly\"}"
  },
  {
    "idx": 15,
    "status_code": 429,
    "ok": false,
    "elapsed_s": 0.288,
    "body": "{\"detail\":\"realtime pipeline is at capacity \u2014 try again shortly\"}"
  },
  {
    "idx": 20,
    "status_code": 429,
    "ok": false,
    "elapsed_s": 0.129,
    "body": "{\"detail\":\"realtime pipeline is at capacity \u2014 try again shortly\"}"
  },
  {
    "idx": 22,
    "status_code": 429,
    "ok": false,
    "elapsed_s": 0.11,
    "body": "{\"detail\":\"realtime pipeline is at capacity \u2014 try again shortly\"}"
  },
  {
    "idx": 23,
    "status_code": 429,
    "ok": false,
    "elapsed_s": 0.028,
    "body": "{\"detail\":\"realtime pipeline is at capacity \u2014 try again shortly\"}"
  },
  {
    "idx": 21,
    "status_code": 429,
    "ok": false,
    "elapsed_s": 0.114,
    "body": "{\"detail\":\"realtime pipeline is at capacity \u2014 try again shortly\"}"
  },
  {
    "idx": 24,
    "status_code": 429,
    "ok": false,
    "elapsed_s": 0.027,
    "body": "{\"detail\":\"realtime pipeline is at capacity \u2014 try again shortly\"}"
  },
  {
    "idx": 29,
    "status_code": 429,
    "ok": false,
    "elapsed_s": 0.044,
    "body": "{\"detail\":\"realtime pipeline is at capacity \u2014 try again shortly\"}"
  },
  {
    "idx": 25,
    "status_code": 429,
    "ok": false,
    "elapsed_s": 0.054,
    "body": "{\"detail\":\"realtime pipeline is at capacity \u2014 try again shortly\"}"
  },
  {
    "idx": 26,
    "status_code": 429,
    "ok": false,
    "elapsed_s": 0.056,
    "body": "{\"detail\":\"realtime pipeline is at capacity \u2014 try again shortly\"}"
  },
  {
    "idx": 28,
    "status_code": 429,
    "ok": false,
    "elapsed_s": 0.055,
    "body": "{\"detail\":\"realtime pipeline is at capacity \u2014 try again shortly\"}"
  },
  {
    "idx": 30,
    "status_code": 429,
    "ok": false,
    "elapsed_s": 0.05,
    "body": "{\"detail\":\"realtime pipeline is at capacity \u2014 try again shortly\"}"
  },
  {
    "idx": 27,
    "status_code": 429,
    "ok": false,
    "elapsed_s": 0.062,
    "body": "{\"detail\":\"realtime pipeline is at capacity \u2014 try again shortly\"}"
  },
  {
    "idx": 31,
    "status_code": 429,
    "ok": false,
    "elapsed_s": 0.051,
    "body": "{\"detail\":\"realtime pipeline is at capacity \u2014 try again shortly\"}"
  }
]
